wayfinder_paths/__init__.py
wayfinder_paths/adapters/__init__.py
wayfinder_paths/adapters/balance_adapter/README.md
wayfinder_paths/adapters/balance_adapter/adapter.py
wayfinder_paths/adapters/balance_adapter/examples.json
wayfinder_paths/adapters/balance_adapter/test_adapter.py
wayfinder_paths/adapters/brap_adapter/README.md
wayfinder_paths/adapters/brap_adapter/__init__.py
wayfinder_paths/adapters/brap_adapter/adapter.py
wayfinder_paths/adapters/brap_adapter/examples.json
wayfinder_paths/adapters/brap_adapter/test_adapter.py
wayfinder_paths/adapters/hyperlend_adapter/__init__.py
wayfinder_paths/adapters/hyperlend_adapter/adapter.py
wayfinder_paths/adapters/hyperlend_adapter/test_adapter.py
wayfinder_paths/adapters/hyperliquid_adapter/__init__.py
wayfinder_paths/adapters/hyperliquid_adapter/adapter.py
wayfinder_paths/adapters/hyperliquid_adapter/executor.py
wayfinder_paths/adapters/hyperliquid_adapter/paired_filler.py
wayfinder_paths/adapters/hyperliquid_adapter/test_adapter.py
wayfinder_paths/adapters/hyperliquid_adapter/test_adapter_live.py
wayfinder_paths/adapters/hyperliquid_adapter/test_executor.py
wayfinder_paths/adapters/hyperliquid_adapter/test_utils.py
wayfinder_paths/adapters/hyperliquid_adapter/utils.py
wayfinder_paths/adapters/ledger_adapter/README.md
wayfinder_paths/adapters/ledger_adapter/__init__.py
wayfinder_paths/adapters/ledger_adapter/adapter.py
wayfinder_paths/adapters/ledger_adapter/examples.json
wayfinder_paths/adapters/ledger_adapter/test_adapter.py
wayfinder_paths/adapters/moonwell_adapter/README.md
wayfinder_paths/adapters/moonwell_adapter/__init__.py
wayfinder_paths/adapters/moonwell_adapter/adapter.py
wayfinder_paths/adapters/moonwell_adapter/test_adapter.py
wayfinder_paths/adapters/pool_adapter/README.md
wayfinder_paths/adapters/pool_adapter/__init__.py
wayfinder_paths/adapters/pool_adapter/adapter.py
wayfinder_paths/adapters/pool_adapter/examples.json
wayfinder_paths/adapters/pool_adapter/test_adapter.py
wayfinder_paths-0.1.23.dist-info/LICENSE
wayfinder_paths-0.1.23.dist-info/METADATA
wayfinder_paths-0.1.23.dist-info/WHEEL
wayfinder_paths-0.1.23.dist-info/RECORD
