Metadata-Version: 2.1
Name: wayfinder-paths
Version: 0.1.23
Summary: Wayfinder Path: strategies and adapters
Author: Wayfinder
Author-email: dev@wayfinder.ai
Requires-Python: >=3.12,<4.0
Classifier: Programming Language :: Python :: 3
Classifier: Programming Language :: Python :: 3.12
Requires-Dist: aiohttp (>=3.13.0,<4.0.0)
Requires-Dist: eth-account (>=0.13.7,<0.14.0)
Requires-Dist: httpx (>=0.28.1,<0.29.0)
Requires-Dist: hyperliquid-felix
Requires-Dist: loguru (>=0.7.3,<0.8.0)
Requires-Dist: numpy (>=1.26.0,<2.0.0)
Requires-Dist: pandas (>=2.2.0,<3.0.0)
Requires-Dist: pydantic (>=2.11.9,<3.0.0)
Requires-Dist: pyyaml (>=6.0.1,<7.0.0)
Requires-Dist: web3 (>=7.13.0,<8.0.0)
